<?xml version="1.0" encoding="utf-8"?>
<odoo>
    <data noupdate="1">
        <!-- Security Groups -->
        <record id="group_hexapay_retention_user" model="res.groups">
            <field name="name">HexaPay Retention User</field>
            
        </record>
        
        <record id="group_hexapay_retention_manager" model="res.groups">
            <field name="name">HexaPay Retention Manager</field>
            
            <field name="implied_ids" eval="[(4, ref('group_hexapay_retention_user'))]"/>
        </record>
    </data>
</odoo>

